comload/__init__.py
comload/__main__.py
comload/constants.py
comload/description.py
comload-0.3.0.dist-info/METADATA
comload-0.3.0.dist-info/WHEEL
comload-0.3.0.dist-info/entry_points.txt
comload-0.3.0.dist-info/RECORD
